package/__init__.py
package/module2.py
package/utils/__init__.py
package/utils/module1.py
package/utils/printing.py
package_iiii-0.0.1.dist-info/METADATA
package_iiii-0.0.1.dist-info/WHEEL
package_iiii-0.0.1.dist-info/top_level.txt
package_iiii-0.0.1.dist-info/RECORD
